Workbook
Name P_Annee: '08_PARAMETRES'!$C$6
Name P_DossierClasseur: '08_PARAMETRES'!$C$7
Name P_NomFichierSource: '08_PARAMETRES'!$C$8
Name P_CheminComplet: '08_PARAMETRES'!$C$9
Name P_CheminSource: '08_PARAMETRES'!$C$10
Name P_FeuilleSource: '08_PARAMETRES'!$C$11
Name P_LongueurCodePoste: '08_PARAMETRES'!$C$12
Name P_SeparateurCodePoste: '08_PARAMETRES'!$C$13
Name P_DateProgramme: '08_PARAMETRES'!$C$16

Sheet 01_PLAN_PREVENTIF
C1: Plan préventif pluriannuel | P1: PROTOTYPE V0.3
C2: Site → Équipe → Poste → Année. Programme préventif par poste ; la GMAO reste la source de référence. | P2: Données 100 % fictives
A4: ="Opérations prévues "&P_Annee -> Opérations prévues 2027 | C4: ="Postes concernés "&P_Annee -> Postes concernés 2027 | E4: Opérations au programme (toutes années) | F4: Postes au programme | H4: Années couvertes | K4: ="OT GMAO "&P_Annee&" (complément)" -> OT GMAO 2027 (complément) | N4: Statut à confirmer | P4: Points de vigilance
A5: =COUNTIF(T_Programme[Année],P_Annee) -> 45 | C5: =SUMPRODUCT((T_Programme[Année]=P_Annee)/COUNTIFS(T_Programme[Code installation],T_Programme[Code installation],T_Programme[Année],T_Programme[Année])) -> 28 | E5: =COUNTA(T_Programme[Code installation]) -> 122 | F5: =SUMPRODUCT((T_Programme[Code installation]<>"")/COUNTIF(T_Programme[Code installation],T_Programme[Code installation]&"")) -> 40 | H5: =MIN(T_Programme[Année])&" – "&MAX(T_Programme[Année]) -> 2026 – 2032 | K5: =IFERROR(SUMIFS(INDEX('02_COUVERTURE_OT'!$A$9:$AZ$200000,0,MATCH("OT distincts (toutes activités)",'02_COUVERTURE_OT'!$A$8:$AZ$8,0)),'02_COUVERTURE_OT'!$A$9:$A$200000,P_Annee),0) -> 18 | N5: =COUNTIF(T_Plan[Statut référentiel],"À confirmer")+COUNTIF(T_Plan[Statut référentiel],"Absent du référentiel") -> 19 | P5: =COUNTIF(T_Plan[Point de vigilance],"?*") -> 5
A6: Année d'analyse | B6: =P_Annee -> 2027 | C6: =IF(SUM(T_Plan[[2026]:[2032]])=COUNTA(T_Programme[Année]),"Contrôle programme : OK ("&COUNTA(T_Programme[Année])&" lignes)","Contrôle programme : VUE À ACTUALISER (source "&COUNTA(T_Programme[Année])&" / vue "&SUM(T_Plan[[2026]:[2032]])&")") -> Contrôle programme : OK (122 lignes) | P6: ● opération prévue · ●×2 lignes identiques · colonne jaune = année d'analyse (08)
A7: Périmètre | B7: Groupe | C7: Code installation | D7: Installation | E7: Opération | F7: Périodicité | G7: 2026 | H7: 2027 | I7: 2028 | J7: 2029 | K7: 2030 | L7: 2031 | M7: 2032 | N7: Code type source | O7: Statut référentiel | P7: Point de vigilance
A8: PERIM_A | B8: GRP_A1 | C8: INST-001 | D8: Installation A1 | E8: =IFERROR(INDEX(T_Referentiel[Libellé affiché],MATCH($N8,T_Referentiel[Valeur source],0)),"À confirmer") -> Contrôle annuel | F8: 1 an | G8: =COUNTIFS(T_Programme[Code installation],$C8,T_Programme[Type opération source],$N8,T_Programme[Périodicité],$F8,T_Programme[Année],G$7) -> 0 | H8: =COUNTIFS(T_Programme[Code installation],$C8,T_Programme[Type opération source],$N8,T_Programme[Périodicité],$F8,T_Programme[Année],H$7) -> 1 | I8: =COUNTIFS(T_Programme[Code installation],$C8,T_Programme[Type opération source],$N8,T_Programme[Périodicité],$F8,T_Programme[Année],I$7) -> 0 | J8: =COUNTIFS(T_Programme[Code installation],$C8,T_Programme[Type opération source],$N8,T_Programme[Périodicité],$F8,T_Programme[Année],J$7) -> 0 | K8: =COUNTIFS(T_Programme[Code installation],$C8,T_Programme[Type opération source],$N8,T_Programme[Périodicité],$F8,T_Programme[Année],K$7) -> 0 | L8: =COUNTIFS(T_Programme[Code installation],$C8,T_Programme[Type opération source],$N8,T_Programme[Périodicité],$F8,T_Programme[Année],L$7) -> 0 | M8: =COUNTIFS(T_Programme[Code installation],$C8,T_Programme[Type opération source],$N8,T_Programme[Périodicité],$F8,T_Programme[Année],M$7) -> 0 | N8: TYPE_A | O8: =IFERROR(INDEX(T_Referentiel[Statut],MATCH($N8,T_Referentiel[Valeur source],0)),"Absent du référentiel") -> Validé pour démo | P8: =IF(COUNTIF(G8:M8,">1")>0,"Doublon potentiel : à confirmer","")
A9: PERIM_A | B9: GRP_A1 | C9: INST-001 | D9: Installation A1 | E9: =IFERROR(INDEX(T_Referentiel[Libellé affiché],MATCH($N9,T_Referentiel[Valeur source],0)),"À confirmer") -> Contrôle filtre | F9: 3 ans | G9: =COUNTIFS(T_Programme[Code installation],$C9,T_Programme[Type opération source],$N9,T_Programme[Périodicité],$F9,T_Programme[Année],G$7) -> 0 | H9: =COUNTIFS(T_Programme[Code installation],$C9,T_Programme[Type opération source],$N9,T_Programme[Périodicité],$F9,T_Programme[Année],H$7) -> 1 | I9: =COUNTIFS(T_Programme[Code installation],$C9,T_Programme[Type opération source],$N9,T_Programme[Périodicité],$F9,T_Programme[Année],I$7) -> 0 | J9: =COUNTIFS(T_Programme[Code installation],$C9,T_Programme[Type opération source],$N9,T_Programme[Périodicité],$F9,T_Programme[Année],J$7) -> 0 | K9: =COUNTIFS(T_Programme[Code installation],$C9,T_Programme[Type opération source],$N9,T_Programme[Périodicité],$F9,T_Programme[Année],K$7) -> 0 | L9: =COUNTIFS(T_Programme[Code installation],$C9,T_Programme[Type opération source],$N9,T_Programme[Périodicité],$F9,T_Programme[Année],L$7) -> 0 | M9: =COUNTIFS(T_Programme[Code installation],$C9,T_Programme[Type opération source],$N9,T_Programme[Périodicité],$F9,T_Programme[Année],M$7) -> 0 | N9: TYPE_C | O9: =IFERROR(INDEX(T_Referentiel[Statut],MATCH($N9,T_Referentiel[Valeur source],0)),"Absent du référentiel") -> Validé pour démo | P9: =IF(COUNTIF(G9:M9,">1")>0,"Doublon potentiel : à confirmer","")
A10: PERIM_A | B10: GRP_A1 | C10: INST-001 | D10: Installation A1 | E10: =IFERROR(INDEX(T_Referentiel[Libellé affiché],MATCH($N10,T_Referentiel[Valeur source],0)),"À confirmer") -> Révision | F10: 6 ans | G10: =COUNTIFS(T_Programme[Code installation],$C10,T_Programme[Type opération source],$N10,T_Programme[Périodicité],$F10,T_Programme[Année],G$7) -> 0 | H10: =COUNTIFS(T_Programme[Code installation],$C10,T_Programme[Type opération source],$N10,T_Programme[Périodicité],$F10,T_Programme[Année],H$7) -> 0 | I10: =COUNTIFS(T_Programme[Code installation],$C10,T_Programme[Type opération source],$N10,T_Programme[Périodicité],$F10,T_Programme[Année],I$7) -> 0 | J10: =COUNTIFS(T_Programme[Code installation],$C10,T_Programme[Type opération source],$N10,T_Programme[Périodicité],$F10,T_Programme[Année],J$7) -> 1 | K10: =COUNTIFS(T_Programme[Code installation],$C10,T_Programme[Type opération source],$N10,T_Programme[Périodicité],$F10,T_Programme[Année],K$7) -> 0 | L10: =COUNTIFS(T_Programme[Code installation],$C10,T_Programme[Type opération source],$N10,T_Programme[Périodicité],$F10,T_Programme[Année],L$7) -> 0 | M10: =COUNTIFS(T_Programme[Code installation],$C10,T_Programme[Type opération source],$N10,T_Programme[Périodicité],$F10,T_Programme[Année],M$7) -> 0 | N10: TYPE_D | O10: =IFERROR(INDEX(T_Referentiel[Statut],MATCH($N10,T_Referentiel[Valeur source],0)),"Absent du référentiel") -> Validé pour démo | P10: =IF(COUNTIF(G10:M10,">1")>0,"Doublon potentiel : à confirmer","")
A11: PERIM_A | B11: GRP_A1 | C11: INST-001 | D11: Installation A1 | E11: =IFERROR(INDEX(T_Referentiel[Libellé affiché],MATCH($N11,T_Referentiel[Valeur source],0)),"À confirmer") -> Opération spécifique | F11: 2 ans | G11: =COUNTIFS(T_Programme[Code installation],$C11,T_Programme[Type opération source],$N11,T_Programme[Périodicité],$F11,T_Programme[Année],G$7) -> 0 | H11: =COUNTIFS(T_Programme[Code installation],$C11,T_Programme[Type opération source],$N11,T_Programme[Périodicité],$F11,T_Programme[Année],H$7) -> 1 | I11: =COUNTIFS(T_Programme[Code installation],$C11,T_Programme[Type opération source],$N11,T_Programme[Périodicité],$F11,T_Programme[Année],I$7) -> 0 | J11: =COUNTIFS(T_Programme[Code installation],$C11,T_Programme[Type opération source],$N11,T_Programme[Périodicité],$F11,T_Programme[Année],J$7) -> 0 | K11: =COUNTIFS(T_Programme[Code installation],$C11,T_Programme[Type opération source],$N11,T_Programme[Périodicité],$F11,T_Programme[Année],K$7) -> 0 | L11: =COUNTIFS(T_Programme[Code installation],$C11,T_Programme[Type opération source],$N11,T_Programme[Périodicité],$F11,T_Programme[Année],L$7) -> 0 | M11: =COUNTIFS(T_Programme[Code installation],$C11,T_Programme[Type opération source],$N11,T_Programme[Périodicité],$F11,T_Programme[Année],M$7) -> 0 | N11: TYPE_E | O11: =IFERROR(INDEX(T_Referentiel[Statut],MATCH($N11,T_Referentiel[Valeur source],0)),"Absent du référentiel") -> À confirmer | P11: =IF(COUNTIF(G11:M11,">1")>0,"Doublon potentiel : à confirmer","")
A12: PERIM_A | B12: GRP_A1 | C12: INST-002 | D12: Installation B1 | E12: =IFERROR(INDEX(T_Referentiel[Libellé affiché],MATCH($N12,T_Referentiel[Valeur source],0)),"À confirmer") -> Contrôle annuel | F12: 1 an | G12: =COUNTIFS(T_Programme[Code installation],$C12,T_Programme[Type opération source],$N12,T_Programme[Périodicité],$F12,T_Programme[Année],G$7) -> 0 | H12: =COUNTIFS(T_Programme[Code installation],$C12,T_Programme[Type opération source],$N12,T_Programme[Périodicité],$F12,T_Programme[Année],H$7) -> 0 | I12: =COUNTIFS(T_Programme[Code installation],$C12,T_Programme[Type opération source],$N12,T_Programme[Périodicité],$F12,T_Programme[Année],I$7) -> 0 | J12: =COUNTIFS(T_Programme[Code installation],$C12,T_Programme[Type opération source],$N12,T_Programme[Périodicité],$F12,T_Programme[Année],J$7) -> 1 | K12: =COUNTIFS(T_Programme[Code installation],$C12,T_Programme[Type opération source],$N12,T_Programme[Périodicité],$F12,T_Programme[Année],K$7) -> 0 | L12: =COUNTIFS(T_Programme[Code installation],$C12,T_Programme[Type opération source],$N12,T_Programme[Périodicité],$F12,T_Programme[Année],L$7) -> 0 | M12: =COUNTIFS(T_Programme[Code installation],$C12,T_Programme[Type opération source],$N12,T_Programme[Périodicité],$F12,T_Programme[Année],M$7) -> 0 | N12: TYPE_A | O12: =IFERROR(INDEX(T_Referentiel[Statut],MATCH($N12,T_Referentiel[Valeur source],0)),"Absent du référentiel") -> Validé pour démo | P12: =IF(COUNTIF(G12:M12,">1")>0,"Doublon potentiel : à confirmer","")
A13: PERIM_A | B13: GRP_A1 | C13: INST-002 | D13: Installation B1 | E13: =IFERROR(INDEX(T_Referentiel[Libellé affiché],MATCH($N13,T_Referentiel[Valeur source],0)),"À confirmer") -> Essai de conformité | F13: 2 ans | G13: =COUNTIFS(T_Programme[Code installation],$C13,T_Programme[Type opération source],$N13,T_Programme[Périodicité],$F13,T_Programme[Année],G$7) -> 0 | H13: =COUNTIFS(T_Programme[Code installation],$C13,T_Programme[Type opération source],$N13,T_Programme[Périodicité],$F13,T_Programme[Année],H$7) -> 0 | I13: =COUNTIFS(T_Programme[Code installation],$C13,T_Programme[Type opération source],$N13,T_Programme[Périodicité],$F13,T_Programme[Année],I$7) -> 1 | J13: =COUNTIFS(T_Programme[Code installation],$C13,T_Programme[Type opération source],$N13,T_Programme[Périodicité],$F13,T_Programme[Année],J$7) -> 0 | K13: =COUNTIFS(T_Programme[Code installation],$C13,T_Programme[Type opération source],$N13,T_Programme[Périodicité],$F13,T_Programme[Année],K$7) -> 0 | L13: =COUNTIFS(T_Programme[Code installation],$C13,T_Programme[Type opération source],$N13,T_Programme[Périodicité],$F13,T_Programme[Année],L$7) -> 0 | M13: =COUNTIFS(T_Programme[Code installation],$C13,T_Programme[Type opération source],$N13,T_Programme[Périodicité],$F13,T_Programme[Année],M$7) -> 0 | N13: TYPE_B | O13: =IFERROR(INDEX(T_Referentiel[Statut],MATCH($N13,T_Referentiel[Valeur source],0)),"Absent du référentiel") -> Validé pour démo | P13: =IF(COUNTIF(G13:M13,">1")>0,"Doublon potentiel : à confirmer","")
A14: PERIM_A | B14: GRP_A1 | C14: INST-002 | D14: Installation B1 | E14: =IFERROR(INDEX(T_Referentiel[Libellé affiché],MATCH($N14,T_Referentiel[Valeur source],0)),"À confirmer") -> Révision | F14: 6 ans | G14: =COUNTIFS(T_Programme[Code installation],$C14,T_Programme[Type opération source],$N14,T_Programme[Périodicité],$F14,T_Programme[Année],G$7) -> 0 | H14: =COUNTIFS(T_Programme[Code installation],$C14,T_Programme[Type opération source],$N14,T_Programme[Périodicité],$F14,T_Programme[Année],H$7) -> 1 | I14: =COUNTIFS(T_Programme[Code installation],$C14,T_Programme[Type opération source],$N14,T_Programme[Périodicité],$F14,T_Programme[Année],I$7) -> 0 | J14: =COUNTIFS(T_Programme[Code installation],$C14,T_Programme[Type opération source],$N14,T_Programme[Périodicité],$F14,T_Programme[Année],J$7) -> 0 | K14: =COUNTIFS(T_Programme[Code installation],$C14,T_Programme[Type opération source],$N14,T_Programme[Périodicité],$F14,T_Programme[Année],K$7) -> 0 | L14: =COUNTIFS(T_Programme[Code installation],$C14,T_Programme[Type opération source],$N14,T_Programme[Périodicité],$F14,T_Programme[Année],L$7) -> 0 | M14: =COUNTIFS(T_Programme[Code installation],$C14,T_Programme[Type opération source],$N14,T_Programme[Périodicité],$F14,T_Programme[Année],M$7) -> 0 | N14: TYPE_D | O14: =IFERROR(INDEX(T_Referentiel[Statut],MATCH($N14,T_Referentiel[Valeur source],0)),"Absent du référentiel") -> Validé pour démo | P14: =IF(COUNTIF(G14:M14,">1")>0,"Doublon potentiel : à confirmer","")
A15: PERIM_A | B15: GRP_A1 | C15: INST-003 | D15: Installation C1 | E15: =IFERROR(INDEX(T_Referentiel[Libellé affiché],MATCH($N15,T_Referentiel[Valeur source],0)),"À confirmer") -> Révision | F15: 6 ans | G15: =COUNTIFS(T_Programme[Code installation],$C15,T_Programme[Type opération source],$N15,T_Programme[Périodicité],$F15,T_Programme[Année],G$7) -> 0 | H15: =COUNTIFS(T_Programme[Code installation],$C15,T_Programme[Type opération source],$N15,T_Programme[Périodicité],$F15,T_Programme[Année],H$7) -> 0 | I15: =COUNTIFS(T_Programme[Code installation],$C15,T_Programme[Type opération source],$N15,T_Programme[Périodicité],$F15,T_Programme[Année],I$7) -> 0 | J15: =COUNTIFS(T_Programme[Code installation],$C15,T_Programme[Type opération source],$N15,T_Programme[Périodicité],$F15,T_Programme[Année],J$7) -> 1 | K15: =COUNTIFS(T_Programme[Code installation],$C15,T_Programme[Type opération source],$N15,T_Programme[Périodicité],$F15,T_Programme[Année],K$7) -> 0 | L15: =COUNTIFS(T_Programme[Code installation],$C15,T_Programme[Type opération source],$N15,T_Programme[Périodicité],$F15,T_Programme[Année],L$7) -> 0 | M15: =COUNTIFS(T_Programme[Code installation],$C15,T_Programme[Type opération source],$N15,T_Programme[Périodicité],$F15,T_Programme[Année],M$7) -> 1 | N15: TYPE_D | O15: =IFERROR(INDEX(T_Referentiel[Statut],MATCH($N15,T_Referentiel[Valeur source],0)),"Absent du référentiel") -> Validé pour démo | P15: =IF(COUNTIF(G15:M15,">1")>0,"Doublon potentiel : à confirmer","")
A16: PERIM_A | B16: GRP_A1 | C16: INST-003 | D16: Installation C1 | E16: =IFERROR(INDEX(T_Referentiel[Libellé affiché],MATCH($N16,T_Referentiel[Valeur source],0)),"À confirmer") -> Opération spécifique | F16: 2 ans | G16: =COUNTIFS(T_Programme[Code installation],$C16,T_Programme[Type opération source],$N16,T_Programme[Périodicité],$F16,T_Programme[Année],G$7) -> 0 | H16: =COUNTIFS(T_Programme[Code installation],$C16,T_Programme[Type opération source],$N16,T_Programme[Périodicité],$F16,T_Programme[Année],H$7) -> 0 | I16: =COUNTIFS(T_Programme[Code installation],$C16,T_Programme[Type opération source],$N16,T_Programme[Périodicité],$F16,T_Programme[Année],I$7) -> 0 | J16: =COUNTIFS(T_Programme[Code installation],$C16,T_Programme[Type opération source],$N16,T_Programme[Périodicité],$F16,T_Programme[Année],J$7) -> 1 | K16: =COUNTIFS(T_Programme[Code installation],$C16,T_Programme[Type opération source],$N16,T_Programme[Périodicité],$F16,T_Programme[Année],K$7) -> 0 | L16: =COUNTIFS(T_Programme[Code installation],$C16,T_Programme[Type opération source],$N16,T_Programme[Périodicité],$F16,T_Programme[Année],L$7) -> 1 | M16: =COUNTIFS(T_Programme[Code installation],$C16,T_Programme[Type opération source],$N16,T_Programme[Périodicité],$F16,T_Programme[Année],M$7) -> 0 | N16: TYPE_E | O16: =IFERROR(INDEX(T_Referentiel[Statut],MATCH($N16,T_Referentiel[Valeur source],0)),"Absent du référentiel") -> À confirmer | P16: =IF(COUNTIF(G16:M16,">1")>0,"Doublon potentiel : à confirmer","")
A17: PERIM_A | B17: GRP_A1 | C17: INST-004 | D17: Installation D1 | E17: =IFERROR(INDEX(T_Referentiel[Libellé affiché],MATCH($N17,T_Referentiel[Valeur source],0)),"À confirmer") -> Révision | F17: 6 ans | G17: =COUNTIFS(T_Programme[Code installation],$C17,T_Programme[Type opération source],$N17,T_Programme[Périodicité],$F17,T_Programme[Année],G$7) -> 0 | H17: =COUNTIFS(T_Programme[Code installation],$C17,T_Programme[Type opération source],$N17,T_Programme[Périodicité],$F17,T_Programme[Année],H$7) -> 1 | I17: =COUNTIFS(T_Programme[Code installation],$C17,T_Programme[Type opération source],$N17,T_Programme[Périodicité],$F17,T_Programme[Année],I$7) -> 0 | J17: =COUNTIFS(T_Programme[Code installation],$C17,T_Programme[Type opération source],$N17,T_Programme[Périodicité],$F17,T_Programme[Année],J$7) -> 0 | K17: =COUNTIFS(T_Programme[Code installation],$C17,T_Programme[Type opération source],$N17,T_Programme[Périodicité],$F17,T_Programme[Année],K$7) -> 0 | L17: =COUNTIFS(T_Programme[Code installation],$C17,T_Programme[Type opération source],$N17,T_Programme[Périodicité],$F17,T_Programme[Année],L$7) -> 0 | M17: =COUNTIFS(T_Programme[Code installation],$C17,T_Programme[Type opération source],$N17,T_Programme[Périodicité],$F17,T_Programme[Année],M$7) -> 0 | N17: TYPE_D | O17: =IFERROR(INDEX(T_Referentiel[Statut],MATCH($N17,T_Referentiel[Valeur source],0)),"Absent du référentiel") -> Validé pour démo | P17: =IF(COUNTIF(G17:M17,">1")>0,"Doublon potentiel : à confirmer","")
A18: PERIM_A | B18: GRP_A1 | C18: INST-004 | D18: Installation D1 | E18: =IFERROR(INDEX(T_Referentiel[Libellé affiché],MATCH($N18,T_Referentiel[Valeur source],0)),"À confirmer") -> Opération spécifique | F18: 2 ans | G18: =COUNTIFS(T_Programme[Code installation],$C18,T_Programme[Type opération source],$N18,T_Programme[Périodicité],$F18,T_Programme[Année],G$7) -> 0 | H18: =COUNTIFS(T_Programme[Code installation],$C18,T_Programme[Type opération source],$N18,T_Programme[Périodicité],$F18,T_Programme[Année],H$7) -> 0 | I18: =COUNTIFS(T_Programme[Code installation],$C18,T_Programme[Type opération source],$N18,T_Programme[Périodicité],$F18,T_Programme[Année],I$7) -> 0 | J18: =COUNTIFS(T_Programme[Code installation],$C18,T_Programme[Type opération source],$N18,T_Programme[Périodicité],$F18,T_Programme[Année],J$7) -> 0 | K18: =COUNTIFS(T_Programme[Code installation],$C18,T_Programme[Type opération source],$N18,T_Programme[Périodicité],$F18,T_Programme[Année],K$7) -> 0 | L18: =COUNTIFS(T_Programme[Code installation],$C18,T_Programme[Type opération source],$N18,T_Programme[Périodicité],$F18,T_Programme[Année],L$7) -> 0 | M18: =COUNTIFS(T_Programme[Code installation],$C18,T_Programme[Type opération source],$N18,T_Programme[Périodicité],$F18,T_Programme[Année],M$7) -> 1 | N18: TYPE_E | O18: =IFERROR(INDEX(T_Referentiel[Statut],MATCH($N18,T_Referentiel[Valeur source],0)),"Absent du référentiel") -> À confirmer | P18: =IF(COUNTIF(G18:M18,">1")>0,"Doublon potentiel : à confirmer","")
A19: PERIM_A | B19: GRP_A1 | C19: INST-005 | D19: Installation E1 | E19: =IFERROR(INDEX(T_Referentiel[Libellé affiché],MATCH($N19,T_Referentiel[Valeur source],0)),"À confirmer") -> Contrôle annuel | F19: 1 an | G19: =COUNTIFS(T_Programme[Code installation],$C19,T_Programme[Type opération source],$N19,T_Programme[Périodicité],$F19,T_Programme[Année],G$7) -> 0 | H19: =COUNTIFS(T_Programme[Code installation],$C19,T_Programme[Type opération source],$N19,T_Programme[Périodicité],$F19,T_Programme[Année],H$7) -> 0 | I19: =COUNTIFS(T_Programme[Code installation],$C19,T_Programme[Type opération source],$N19,T_Programme[Périodicité],$F19,T_Programme[Année],I$7) -> 0 | J19: =COUNTIFS(T_Programme[Code installation],$C19,T_Programme[Type opération source],$N19,T_Programme[Périodicité],$F19,T_Programme[Année],J$7) -> 0 | K19: =COUNTIFS(T_Programme[Code installation],$C19,T_Programme[Type opération source],$N19,T_Programme[Périodicité],$F19,T_Programme[Année],K$7) -> 1 | L19: =COUNTIFS(T_Programme[Code installation],$C19,T_Programme[Type opération source],$N19,T_Programme[Périodicité],$F19,T_Programme[Année],L$7) -> 0 | M19: =COUNTIFS(T_Programme[Code installation],$C19,T_Programme[Type opération source],$N19,T_Programme[Périodicité],$F19,T_Programme[Année],M$7) -> 0 | N19: TYPE_A | O19: =IFERROR(INDEX(T_Referentiel[Statut],MATCH($N19,T_Referentiel[Valeur source],0)),"Absent du référentiel") -> Validé pour démo | P19: =IF(COUNTIF(G19:M19,">1")>0,"Doublon potentiel : à confirmer","")
... A111: PERIM_C | B111: GRP_C1 | C111: INST-040 | D111: Installation N2 | E111: =IFERROR(INDEX(T_Referentiel[Libellé affiché],MATCH($N111,T_Referentiel[Valeur source],0)),"À confirmer") -> Contrôle filtre | F111: 3 ans | G111: =COUNTIFS(T_Programme[Code installation],$C111,T_Programme[Type opération source],$N111,T_Programme[Périodicité],$F111,T_Programme[Année],G$7) -> 0 | H111: =COUNTIFS(T_Programme[Code installation],$C111,T_Programme[Type opération source],$N111,T_Programme[Périodicité],$F111,T_Programme[Année],H$7) -> 1 | I111: =COUNTIFS(T_Programme[Code installation],$C111,T_Programme[Type opération source],$N111,T_Programme[Périodicité],$F111,T_Programme[Année],I$7) -> 0 | J111: =COUNTIFS(T_Programme[Code installation],$C111,T_Programme[Type opération source],$N111,T_Programme[Périodicité],$F111,T_Programme[Année],J$7) -> 0 | K111: =COUNTIFS(T_Programme[Code installation],$C111,T_Programme[Type opération source],$N111,T_Programme[Périodicité],$F111,T_Programme[Année],K$7) -> 0 | L111: =COUNTIFS(T_Programme[Code installation],$C111,T_Programme[Type opération source],$N111,T_Programme[Périodicité],$F111,T_Programme[Année],L$7) -> 0 | M111: =COUNTIFS(T_Programme[Code installation],$C111,T_Programme[Type opération source],$N111,T_Programme[Périodicité],$F111,T_Programme[Année],M$7) -> 0 | N111: TYPE_C | O111: =IFERROR(INDEX(T_Referentiel[Statut],MATCH($N111,T_Referentiel[Valeur source],0)),"Absent du référentiel") -> Validé pour démo | P111: =IF(COUNTIF(G111:M111,">1")>0,"Doublon potentiel : à confirmer","")

Sheet 02_COUVERTURE_OT
A1: Couverture OT préventifs (GMAO) | K1: PROTOTYPE V0.3
A2: Nombre d'OT distincts par site, équipe, poste et activité. Complément du plan : aucun rapprochement automatique avec le programme. | K2: Données 100 % fictives
A4: ="OT distincts "&P_Annee -> OT distincts 2027 | C4: ="Postes avec OT "&P_Annee -> Postes avec OT 2027 | E4: =INDEX(T_Ref_Activites[Activité],1) -> PIS | F4: =INDEX(T_Ref_Activites[Activité],2) -> EC | G4: =INDEX(T_Ref_Activites[Activité],3) -> PILOTAGE | H4: =INDEX(T_Ref_Activites[Activité],4) -> FILTRE | I4: =INDEX(T_Ref_Activites[Activité],5) -> REV | J4: OT toutes années | K4: Contrôles à vérifier
A5: =IFERROR(SUMIFS(INDEX('02_COUVERTURE_OT'!$A$9:$AZ$200000,0,MATCH("OT distincts (toutes activités)",'02_COUVERTURE_OT'!$A$8:$AZ$8,0)),'02_COUVERTURE_OT'!$A$9:$A$200000,P_Annee),0) -> 18 | C5: =COUNTIFS('02_COUVERTURE_OT'!$A$9:$A$200000,P_Annee) -> 18 | E5: =IFERROR(SUMIFS(INDEX('02_COUVERTURE_OT'!$A$9:$AZ$200000,0,MATCH(INDEX(T_Ref_Activites[Activité],1),'02_COUVERTURE_OT'!$A$8:$AZ$8,0)),'02_COUVERTURE_OT'!$A$9:$A$200000,P_Annee),0) -> 10 | F5: =IFERROR(SUMIFS(INDEX('02_COUVERTURE_OT'!$A$9:$AZ$200000,0,MATCH(INDEX(T_Ref_Activites[Activité],2),'02_COUVERTURE_OT'!$A$8:$AZ$8,0)),'02_COUVERTURE_OT'!$A$9:$A$200000,P_Annee),0) -> 14 | G5: =IFERROR(SUMIFS(INDEX('02_COUVERTURE_OT'!$A$9:$AZ$200000,0,MATCH(INDEX(T_Ref_Activites[Activité],3),'02_COUVERTURE_OT'!$A$8:$AZ$8,0)),'02_COUVERTURE_OT'!$A$9:$A$200000,P_Annee),0) -> 5 | H5: =IFERROR(SUMIFS(INDEX('02_COUVERTURE_OT'!$A$9:$AZ$200000,0,MATCH(INDEX(T_Ref_Activites[Activité],4),'02_COUVERTURE_OT'!$A$8:$AZ$8,0)),'02_COUVERTURE_OT'!$A$9:$A$200000,P_Annee),0) -> 10 | I5: =IFERROR(SUMIFS(INDEX('02_COUVERTURE_OT'!$A$9:$AZ$200000,0,MATCH(INDEX(T_Ref_Activites[Activité],5),'02_COUVERTURE_OT'!$A$8:$AZ$8,0)),'02_COUVERTURE_OT'!$A$9:$A$200000,P_Annee),0) -> 6 | J5: =IFERROR(SUM(INDEX('02_COUVERTURE_OT'!$A$9:$AZ$200000,0,MATCH("OT distincts (toutes activités)",'02_COUVERTURE_OT'!$A$8:$AZ$8,0))),0) -> 90 | K5: =COUNTIF('08_PARAMETRES'!$G$21:$G$80,"À VÉRIFIER") -> 0
A6: Année d'analyse | B6: =P_Annee -> 2027 | C6: ="Source : "&IFERROR(INDEX('04_DETAIL_OT'!$A$2:$AZ$2,MATCH("Fichier source",'04_DETAIL_OT'!$A$1:$AZ$1,0)),"") -> Source : Instantané de démonstration – MODELE_GMAO_PREV_ANONYMISE.csv | J6: Actualisé le | K6: =IFERROR(INDEX('04_DETAIL_OT'!$A$2:$AZ$2,MATCH("Importé le",'04_DETAIL_OT'!$A$1:$AZ$1,0)),"") -> 46309.508
A7: Chaque chiffre = nombre d'OT distincts. Un OT à plusieurs activités compte une fois dans chacune de ses colonnes, et une seule fois dans « OT distincts (toutes activités) ».
A8: Année planifiée | B8: Site | C8: Équipe | D8: Code poste | E8: PIS | F8: EC | G8: PILOTAGE | H8: FILTRE | I8: REV | J8: OT distincts (toutes activités) | K8: OT avec point de contrôle
A9: 2026 | B9: SITE01 | C9: EQ1 | D9: G-I-A1100 | E9: 1 | F9: 1 | G9: 0 | H9: 0 | I9: 0 | J9: 1 | K9: 0
A10: 2026 | B10: SITE01 | C10: EQ1 | D10: G-I-A1200 | E10: 0 | F10: 1 | G10: 0 | H10: 0 | I10: 1 | J10: 1 | K10: 0
A11: 2026 | B11: SITE01 | C11: EQ1 | D11: G-I-A1300 | E11: 1 | F11: 1 | G11: 1 | H11: 1 | I11: 0 | J11: 1 | K11: 0
A12: 2026 | B12: SITE01 | C12: EQ2 | D12: G-I-A2100 | E12: 0 | F12: 1 | G12: 0 | H12: 0 | I12: 1 | J12: 1 | K12: 0
A13: 2026 | B13: SITE01 | C13: EQ2 | D13: G-I-A2200 | E13: 1 | F13: 1 | G13: 1 | H13: 1 | I13: 0 | J13: 1 | K13: 0
A14: 2026 | B14: SITE01 | C14: EQ2 | D14: G-I-A2300 | E14: 0 | F14: 1 | G14: 0 | H14: 1 | I14: 0 | J14: 1 | K14: 0
A15: 2026 | B15: SITE01 | C15: EQ3 | D15: G-I-A3100 | E15: 1 | F15: 1 | G15: 1 | H15: 1 | I15: 0 | J15: 1 | K15: 0
A16: 2026 | B16: SITE01 | C16: EQ3 | D16: G-I-A3200 | E16: 0 | F16: 1 | G16: 0 | H16: 1 | I16: 0 | J16: 1 | K16: 0
A17: 2026 | B17: SITE01 | C17: EQ3 | D17: G-I-A3300 | E17: 1 | F17: 0 | G17: 0 | H17: 0 | I17: 1 | J17: 1 | K17: 0
A18: 2026 | B18: SITE02 | C18: EQ1 | D18: G-I-B1100 | E18: 0 | F18: 1 | G18: 0 | H18: 0 | I18: 1 | J18: 1 | K18: 0
A19: 2026 | B19: SITE02 | C19: EQ1 | D19: G-I-B1200 | E19: 1 | F19: 1 | G19: 1 | H19: 1 | I19: 0 | J19: 1 | K19: 0
A20: 2026 | B20: SITE02 | C20: EQ1 | D20: G-I-B1300 | E20: 0 | F20: 1 | G20: 0 | H20: 1 | I20: 0 | J20: 1 | K20: 0
... A98: 2027 | B98: SITE10 | C98: EQ3 | D98: G-I-J3300 | E98: 1 | F98: 0 | G98: 0 | H98: 0 | I98: 0 | J98: 1 | K98: 0

Sheet 03_DETAIL_PROGRAMME
A1: Périmètre | B1: Groupe | C1: Année | D1: Code installation | E1: Installation | F1: Périodicité | G1: Type opération source
A2: PERIM_A | B2: GRP_A1 | C2: 2029 | D2: INST-001 | E2: Installation A1 | F2: 6 ans | G2: TYPE_D
A3: PERIM_A | B3: GRP_A1 | C3: 2027 | D3: INST-001 | E3: Installation A1 | F3: 3 ans | G3: TYPE_C
A4: PERIM_A | B4: GRP_A1 | C4: 2027 | D4: INST-001 | E4: Installation A1 | F4: 1 an | G4: TYPE_A
A5: PERIM_A | B5: GRP_A1 | C5: 2027 | D5: INST-001 | E5: Installation A1 | F5: 2 ans | G5: TYPE_E
A6: PERIM_A | B6: GRP_A1 | C6: 2027 | D6: INST-002 | E6: Installation B1 | F6: 6 ans | G6: TYPE_D
A7: PERIM_A | B7: GRP_A1 | C7: 2028 | D7: INST-002 | E7: Installation B1 | F7: 2 ans | G7: TYPE_B
A8: PERIM_A | B8: GRP_A1 | C8: 2029 | D8: INST-002 | E8: Installation B1 | F8: 1 an | G8: TYPE_A
A9: PERIM_A | B9: GRP_A1 | C9: 2029 | D9: INST-003 | E9: Installation C1 | F9: 2 ans | G9: TYPE_E
A10: PERIM_A | B10: GRP_A1 | C10: 2031 | D10: INST-003 | E10: Installation C1 | F10: 2 ans | G10: TYPE_E
A11: PERIM_A | B11: GRP_A1 | C11: 2029 | D11: INST-003 | E11: Installation C1 | F11: 6 ans | G11: TYPE_D
A12: PERIM_A | B12: GRP_A1 | C12: 2032 | D12: INST-003 | E12: Installation C1 | F12: 6 ans | G12: TYPE_D
A13: PERIM_A | B13: GRP_A1 | C13: 2027 | D13: INST-004 | E13: Installation D1 | F13: 6 ans | G13: TYPE_D
... A123: PERIM_C | B123: GRP_C1 | C123: 2027 | D123: INST-040 | E123: Installation N2 | F123: 1 an | G123: TYPE_A

Sheet 04_DETAIL_OT
A1: Ordre | B1: Activité atomique | C1: Année planifiée | D1: Groupe gestionnaires | E1: Poste travail princ. | F1: Code poste | G1: Contrôle qualité | H1: Ligne export | I1: Créé le | J1: Ordre supérieur | K1: Type d'ordre | L1: Type de travail | M1: Avis | N1: Désignation | O1: Statut utilisateur | P1: Statut système | Q1: Saisi par | R1: Total coûts réels | S1: Secteur exploitation | T1: Date début planifiée | U1: Code site | V1: Poste technique | W1: Désign.poste techn. | X1: Équipement | Y1: Groupe de gamme principale | Z1: Compteur de groupe de gamme principale | AA1: Date modif. fiche ordre | AB1: Typologie | AC1: Activité | AD1: Ordre d'affichage activité | AE1: Nb lignes export de l'OT | AF1: Occurrences Ordre+Activité | AG1: Lignes export regroupées | AH1: Écarts de structure | AI1: Fichier source | AJ1: Importé le
A2: 910000001 | B2: EC | C2: 2026 | D2: SITE01 | E2: EQ1 | F2: G-I-A1100 | H2: 2 | I2: 45991 | K2: ZPR2 | L2: PRE | N2: Maintenance préventive fictive EC+PIS - poste G-I-A1100 | O2: ACTI | P2: STAT_SYS_A | Q2: USER01 | R2: 175 | S2: EQ1 | T2: 46058 | U2: TECH-01 | V2: G-I-A1100-FILT01 | W2: Équipement fictif 01-1-1 | X2: EQ-01-1-01 | Y2: GG-PREV | Z2: 1 | AA2: 46047 | AB2: COUPURE | AC2: EC+PIS | AD2: 2 | AE2: 1 | AF2: 1 | AI2: Instantané de démonstration – MODELE_GMAO_PREV_ANONYMISE.csv | AJ2: 46309.508
A3: 910000001 | B3: PIS | C3: 2026 | D3: SITE01 | E3: EQ1 | F3: G-I-A1100 | H3: 2 | I3: 45991 | K3: ZPR2 | L3: PRE | N3: Maintenance préventive fictive EC+PIS - poste G-I-A1100 | O3: ACTI | P3: STAT_SYS_A | Q3: USER01 | R3: 175 | S3: EQ1 | T3: 46058 | U3: TECH-01 | V3: G-I-A1100-FILT01 | W3: Équipement fictif 01-1-1 | X3: EQ-01-1-01 | Y3: GG-PREV | Z3: 1 | AA3: 46047 | AB3: COUPURE | AC3: EC+PIS | AD3: 1 | AE3: 1 | AF3: 1 | AI3: Instantané de démonstration – MODELE_GMAO_PREV_ANONYMISE.csv | AJ3: 46309.508
A4: 910000002 | B4: EC | C4: 2026 | D4: SITE01 | E4: EQ1 | F4: G-I-A1200 | H4: 3 | I4: 46013 | K4: ZPR2 | L4: PRE | N4: Maintenance préventive fictive EC+REV - poste G-I-A1200 | O4: TERM | P4: STAT_SYS_A | Q4: USER01 | R4: 185 | S4: EQ1 | T4: 46087 | U4: TECH-01 | V4: G-I-A1200-FILT01 | W4: Équipement fictif 01-1-2 | X4: EQ-01-1-02 | Y4: GG-PREV | Z4: 2 | AA4: 46075 | AB4: SECTIONNEMENT | AC4: EC+REV | AD4: 2 | AE4: 1 | AF4: 1 | AI4: Instantané de démonstration – MODELE_GMAO_PREV_ANONYMISE.csv | AJ4: 46309.508
A5: 910000002 | B5: REV | C5: 2026 | D5: SITE01 | E5: EQ1 | F5: G-I-A1200 | H5: 3 | I5: 46013 | K5: ZPR2 | L5: PRE | N5: Maintenance préventive fictive EC+REV - poste G-I-A1200 | O5: TERM | P5: STAT_SYS_A | Q5: USER01 | R5: 185 | S5: EQ1 | T5: 46087 | U5: TECH-01 | V5: G-I-A1200-FILT01 | W5: Équipement fictif 01-1-2 | X5: EQ-01-1-02 | Y5: GG-PREV | Z5: 2 | AA5: 46075 | AB5: SECTIONNEMENT | AC5: EC+REV | AD5: 5 | AE5: 1 | AF5: 1 | AI5: Instantané de démonstration – MODELE_GMAO_PREV_ANONYMISE.csv | AJ5: 46309.508
A6: 910000003 | B6: EC | C6: 2026 | D6: SITE01 | E6: EQ1 | F6: G-I-A1300 | H6: 4 | I6: 46038 | K6: ZPR2 | L6: PRE | N6: Maintenance préventive fictive EC+PIS+PILOTAGE+FILTRE - poste G-I-A1300 | O6: ACTI | P6: STAT_SYS_A | Q6: USER01 | R6: 195 | S6: EQ1 | T6: 46119 | U6: TECH-01 | V6: G-I-A1300-SEC01 | W6: Équipement fictif 01-1-3 | X6: EQ-01-1-03 | Y6: GG-PREV | Z6: 3 | AA6: 46106 | AB6: COMPTAGE | AC6: EC+PIS+PILOTAGE+FILTRE | AD6: 2 | AE6: 1 | AF6: 1 | AI6: Instantané de démonstration – MODELE_GMAO_PREV_ANONYMISE.csv | AJ6: 46309.508
A7: 910000003 | B7: PIS | C7: 2026 | D7: SITE01 | E7: EQ1 | F7: G-I-A1300 | H7: 4 | I7: 46038 | K7: ZPR2 | L7: PRE | N7: Maintenance préventive fictive EC+PIS+PILOTAGE+FILTRE - poste G-I-A1300 | O7: ACTI | P7: STAT_SYS_A | Q7: USER01 | R7: 195 | S7: EQ1 | T7: 46119 | U7: TECH-01 | V7: G-I-A1300-SEC01 | W7: Équipement fictif 01-1-3 | X7: EQ-01-1-03 | Y7: GG-PREV | Z7: 3 | AA7: 46106 | AB7: COMPTAGE | AC7: EC+PIS+PILOTAGE+FILTRE | AD7: 1 | AE7: 1 | AF7: 1 | AI7: Instantané de démonstration – MODELE_GMAO_PREV_ANONYMISE.csv | AJ7: 46309.508
A8: 910000003 | B8: PILOTAGE | C8: 2026 | D8: SITE01 | E8: EQ1 | F8: G-I-A1300 | H8: 4 | I8: 46038 | K8: ZPR2 | L8: PRE | N8: Maintenance préventive fictive EC+PIS+PILOTAGE+FILTRE - poste G-I-A1300 | O8: ACTI | P8: STAT_SYS_A | Q8: USER01 | R8: 195 | S8: EQ1 | T8: 46119 | U8: TECH-01 | V8: G-I-A1300-SEC01 | W8: Équipement fictif 01-1-3 | X8: EQ-01-1-03 | Y8: GG-PREV | Z8: 3 | AA8: 46106 | AB8: COMPTAGE | AC8: EC+PIS+PILOTAGE+FILTRE | AD8: 3 | AE8: 1 | AF8: 1 | AI8: Instantané de démonstration – MODELE_GMAO_PREV_ANONYMISE.csv | AJ8: 46309.508
A9: 910000003 | B9: FILTRE | C9: 2026 | D9: SITE01 | E9: EQ1 | F9: G-I-A1300 | H9: 4 | I9: 46038 | K9: ZPR2 | L9: PRE | N9: Maintenance préventive fictive EC+PIS+PILOTAGE+FILTRE - poste G-I-A1300 | O9: ACTI | P9: STAT_SYS_A | Q9: USER01 | R9: 195 | S9: EQ1 | T9: 46119 | U9: TECH-01 | V9: G-I-A1300-SEC01 | W9: Équipement fictif 01-1-3 | X9: EQ-01-1-03 | Y9: GG-PREV | Z9: 3 | AA9: 46106 | AB9: COMPTAGE | AC9: EC+PIS+PILOTAGE+FILTRE | AD9: 4 | AE9: 1 | AF9: 1 | AI9: Instantané de démonstration – MODELE_GMAO_PREV_ANONYMISE.csv | AJ9: 46309.508
A10: 910000004 | B10: EC | C10: 2026 | D10: SITE01 | E10: EQ2 | F10: G-I-A2100 | H10: 5 | I10: 46019 | K10: ZPR2 | L10: PRE | N10: Maintenance préventive fictive EC+REV - poste G-I-A2100 | O10: TERM | P10: STAT_SYS_A | Q10: USER02 | R10: 215 | S10: EQ2 | T10: 46086 | U10: TECH-01 | V10: G-I-A2100-VAN01 | W10: Équipement fictif 01-2-1 | X10: EQ-01-2-01 | Y10: GG-PREV | Z10: 1 | AA10: 46075 | AB10: COUPURE | AC10: EC+REV | AD10: 2 | AE10: 1 | AF10: 1 | AI10: Instantané de démonstration – MODELE_GMAO_PREV_ANONYMISE.csv | AJ10: 46309.508
A11: 910000004 | B11: REV | C11: 2026 | D11: SITE01 | E11: EQ2 | F11: G-I-A2100 | H11: 5 | I11: 46019 | K11: ZPR2 | L11: PRE | N11: Maintenance préventive fictive EC+REV - poste G-I-A2100 | O11: TERM | P11: STAT_SYS_A | Q11: USER02 | R11: 215 | S11: EQ2 | T11: 46086 | U11: TECH-01 | V11: G-I-A2100-VAN01 | W11: Équipement fictif 01-2-1 | X11: EQ-01-2-01 | Y11: GG-PREV | Z11: 1 | AA11: 46075 | AB11: COUPURE | AC11: EC+REV | AD11: 5 | AE11: 1 | AF11: 1 | AI11: Instantané de démonstration – MODELE_GMAO_PREV_ANONYMISE.csv | AJ11: 46309.508
A12: 910000005 | B12: EC | C12: 2026 | D12: SITE01 | E12: EQ2 | F12: G-I-A2200 | H12: 6 | I12: 46044 | K12: ZPR2 | L12: PRE | N12: Maintenance préventive fictive EC+PIS+PILOTAGE+FILTRE - poste G-I-A2200 | O12: ACTI | P12: STAT_SYS_A | Q12: USER02 | R12: 225 | S12: EQ2 | T12: 46118 | U12: TECH-01 | V12: G-I-A2200-VAN01 | W12: Équipement fictif 01-2-2 | X12: EQ-01-2-02 | Y12: GG-PREV | Z12: 2 | AA12: 46106 | AB12: SECTIONNEMENT | AC12: EC+PIS+PILOTAGE+FILTRE | AD12: 2 | AE12: 1 | AF12: 1 | AI12: Instantané de démonstration – MODELE_GMAO_PREV_ANONYMISE.csv | AJ12: 46309.508
A13: 910000005 | B13: PIS | C13: 2026 | D13: SITE01 | E13: EQ2 | F13: G-I-A2200 | H13: 6 | I13: 46044 | K13: ZPR2 | L13: PRE | N13: Maintenance préventive fictive EC+PIS+PILOTAGE+FILTRE - poste G-I-A2200 | O13: ACTI | P13: STAT_SYS_A | Q13: USER02 | R13: 225 | S13: EQ2 | T13: 46118 | U13: TECH-01 | V13: G-I-A2200-VAN01 | W13: Équipement fictif 01-2-2 | X13: EQ-01-2-02 | Y13: GG-PREV | Z13: 2 | AA13: 46106 | AB13: SECTIONNEMENT | AC13: EC+PIS+PILOTAGE+FILTRE | AD13: 1 | AE13: 1 | AF13: 1 | AI13: Instantané de démonstration – MODELE_GMAO_PREV_ANONYMISE.csv | AJ13: 46309.508
... A181: 910000090 | B181: PIS | C181: 2027 | D181: SITE10 | E181: EQ3 | F181: G-I-J3300 | H181: 91 | I181: 46473 | K181: ZPR2 | L181: PRE | N181: Maintenance préventive fictive PIS - poste G-I-J3300 | O181: TERM | P181: STAT_SYS_A | Q181: USER03 | R181: 1400 | S181: EQ3 | T181: 46554 | U181: TECH-10 | V181: G-I-J3300-REG01 | W181: Équipement fictif 10-3-3 | X181: EQ-10-3-03 | Y181: GG-PREV | Z181: 3 | AA181: 46541 | AB181: FILTRE | AC181: PIS | AD181: 1 | AE181: 1 | AF181: 1 | AI181: Instantané de démonstration – MODELE_GMAO_PREV_ANONYMISE.csv | AJ181: 46309.508

Sheet 05_REFERENTIEL
A1: Référentiels | V1: PROTOTYPE V0.3
A2: Correspondances de libellés. Corriger un référentiel corrige les vues ; rien n'est déduit des données.
A5: Types d'opération du programme | I5: Activités GMAO | N5: Sites et équipes connus | R5: Correspondance postes programme ↔ GMAO
A6: Lus par 01_PLAN_PREVENTIF (Opération, Statut). Copie du référentiel fictif. | I6: Une activité absente d'ici est signalée « inconnue » à l'import. Libellés non fournis. | N6: Tout autre couple est signalé « Nouveau site » ou « Nouvelle équipe ». | R6: À construire avec le métier. Prépare la future comparaison prévu / OT ; non utilisée.
A8: Valeur source | B8: Libellé affiché | C8: Famille | D8: Périodicité indicative | E8: Référence technique fictive | F8: Description courte | G8: Statut | I8: Activité | J8: Libellé | K8: Statut | L8: Hypothèse de correspondance programme (non appliquée) | N8: Site | O8: Équipe | P8: Statut | R8: Code installation (programme) | S8: Installation (programme) | T8: Code poste (GMAO) | U8: Statut | V8: Commentaire
A9: TYPE_A | B9: Contrôle annuel | C9: Contrôle | D9: 1 an | E9: REF-001 | F9: Contrôle périodique de démonstration. | G9: Validé pour démo | I9: PIS | J9: À confirmer | K9: Observée dans l'export modèle | N9: SITE01 | O9: EQ1 | P9: Observé dans l'export modèle
A10: TYPE_B | B10: Essai de conformité | C10: Contrôle | D10: 2 ans | E10: REF-002 | F10: Essai périodique de démonstration. | G10: Validé pour démo | I10: EC | J10: À confirmer | K10: Observée dans l'export modèle | N10: SITE01 | O10: EQ2 | P10: Observé dans l'export modèle
A11: TYPE_C | B11: Contrôle filtre | C11: Contrôle | D11: 3 ans | E11: REF-003 | F11: Contrôle filtre de démonstration. | G11: Validé pour démo | I11: PILOTAGE | J11: À confirmer | K11: Observée dans l'export modèle | N11: SITE01 | O11: EQ3 | P11: Observé dans l'export modèle
A12: TYPE_D | B12: Révision | C12: Révision | D12: 6 ans | E12: REF-004 | F12: Révision périodique de démonstration. | G12: Validé pour démo | I12: FILTRE | J12: À confirmer | K12: Observée dans l'export modèle | L12: TYPE_C « Contrôle filtre » ? | N12: SITE02 | O12: EQ1 | P12: Observé dans l'export modèle
A13: TYPE_E | B13: Opération spécifique | C13: Autre | D13: 2 ans | E13: À confirmer | F13: Exemple volontairement incomplet pour tester la gestion des inconnues. | G13: À confirmer | I13: REV | J13: À confirmer | K13: Observée dans l'export modèle | L13: TYPE_D « Révision » ? | N13: SITE02 | O13: EQ2 | P13: Observé dans l'export modèle
N14: SITE02 | O14: EQ3 | P14: Observé dans l'export modèle
N15: SITE03 | O15: EQ1 | P15: Observé dans l'export modèle
N16: SITE03 | O16: EQ2 | P16: Observé dans l'export modèle
N17: SITE03 | O17: EQ3 | P17: Observé dans l'export modèle
N18: SITE04 | O18: EQ1 | P18: Observé dans l'export modèle
N19: SITE04 | O19: EQ2 | P19: Observé dans l'export modèle
N20: SITE04 | O20: EQ3 | P20: Observé dans l'export modèle
N21: SITE05 | O21: EQ1 | P21: Observé dans l'export modèle
N22: SITE05 | O22: EQ2 | P22: Observé dans l'export modèle
N23: SITE05 | O23: EQ3 | P23: Observé dans l'export modèle
N24: SITE06 | O24: EQ1 | P24: Observé dans l'export modèle
N25: SITE06 | O25: EQ2 | P25: Observé dans l'export modèle
... N38: SITE10 | O38: EQ3 | P38: Observé dans l'export modèle

Sheet 06_AVIS_UTILISATEURS
A1: Avis utilisateurs | H1: PROTOTYPE V0.3
A2: Vos retours orientent la version suivante. Une ligne = une remarque.
A5: Questions pour guider vos retours
A6: • | B6: Utile | D6: Quelles colonnes ou informations vous servent vraiment ?
A7: • | B7: Inutile | D7: Qu'est-ce qui pourrait être retiré ou simplifié ?
A8: • | B8: Information manquante | D8: Que vous manque-t-il pour programmer l'année ?
A9: • | B9: Filtre indispensable | D9: Sur quoi devez-vous pouvoir filtrer ou trier ?
A10: • | B10: Besoin spécifique | D10: Un besoin propre à votre site ou à votre équipe ?
A11: • | B11: Saisie / commentaires | D11: Avez-vous besoin de saisir ou de commenter ? Quoi, et qui ?
A12: • | B12: Donnée GMAO à rechercher | D12: Quelles données faudrait-il récupérer dans l'extraction GMAO ?
A13: • | B13: Couverture OT | D13: La vue 02 répond-elle à « mes OT préventifs sont-ils dans la GMAO ? » ?
A15: Comment remplir : une ligne par remarque dans le tableau ci-dessous (cellules blanches). Thème, Priorité : listes déroulantes. La ligne grisée est un exemple à écraser.
A17: Date | B17: Contributeur (nom, fonction) | C17: Site / périmètre | D17: Thème | E17: Remarque | F17: Priorité | G17: Élément concerné (onglet, colonne) | H17: Suite donnée (équipe projet)
A18: 46308 | B18: EXEMPLE – responsable d'exploitation | C18: PERIM_A | D18: Couverture OT | E18: Voir dans la couverture les postes du plan qui n'ont encore aucun OT. | F18: Moyenne | G18: 02_COUVERTURE_OT

Sheet 07_POINTS_A_VALIDER
A1: Points à valider | G1: PROTOTYPE V0.3
A2: Questions métier et hypothèses relevées dans les sources fictives. Rien n'a été corrigé ni supprimé.
A5: ="Contrôles automatiques de l'import GMAO : "&COUNTIF('08_PARAMETRES'!$G$21:$G$80,"À VÉRIFIER")&" à vérifier (détail dans 08_PARAMETRES)." -> Contrôles automatiques de l'import GMAO : 0 à vérifier (détail dans 08_PARAMETRES).
A7: N° | B7: Thème | C7: Constat (dans les sources) | D7: Traitement dans la V0.3 | E7: Question à trancher | F7: Statut | G7: Décision / réponse
A8: 1 | B8: Hiérarchie | C8: Le programme fournit « Périmètre » et « Groupe » ; l'extraction GMAO, « Groupe gestionnaires » (site) et « Poste travail princ. » (équipe). | D8: Colonnes du programme affichées sous leurs noms d'origine. | E8: Périmètre = Site et Groupe = Équipe ? Avec quels libellés lisibles ? | F8: À confirmer
A9: 2 | B9: Rapprochement | C9: Les postes du programme (INST-xxx) et les codes poste GMAO (G-I-A1100…) n'ont aucune clé commune dans les sources fictives. | D9: Pas de comparaison prévu / OT. Table T_Correspondance_Postes préparée (05), vide. | E9: Quelle clé relie un poste du programme à un code poste GMAO ? Qui la maintient ? | F9: À confirmer
A10: 3 | B10: Activités | C10: Activités observées : PIS, EC, PILOTAGE, FILTRE, REV. Aucun libellé ni correspondance avec les types du programme n'est fourni. | D10: Codes repris tels quels ; libellés « À confirmer » ; hypothèses FILTRE → TYPE_C et REV → TYPE_D notées, non appliquées. | E10: Que signifient EC, PIS, PILOTAGE ? Quelle correspondance avec les opérations du programme ? | F10: À confirmer
A11: 4 | B11: Code poste | C11: Règle du test manuel : 9 premiers caractères du Poste technique. Dans le modèle, le 10e caractère est toujours « - » (ex. G-I-A1100-FILT01). | D11: Règle paramétrée (08) ; poste vide, trop court ou sans « - » en 10e position signalé. | E11: La règle est-elle valable pour tous les sites ? Le séparateur est-il toujours « - » ? | F11: À confirmer
A12: 5 | B12: Site | C12: « Code site » (TECH-01…) correspond un pour un à « Groupe gestionnaires » (SITE01…) dans le modèle. | D12: Site = Groupe gestionnaires, comme dans le test manuel. | E12: Quel champ porte le site de référence ? « Code site » doit-il être affiché ? | F12: À confirmer
A13: 6 | B13: Équipe | C13: « Secteur exploitation » porte exactement les mêmes valeurs que « Poste travail princ. » sur les 90 lignes du modèle. | D13: Équipe = Poste travail princ., comme dans le test manuel. | E13: Les deux champs sont-ils toujours identiques dans l'extraction réelle ? | F13: À confirmer
A14: 7 | B14: Périmètre de l'extraction | C14: Toutes les lignes du modèle sont « Type d'ordre » ZPR2 et « Type de travail » PRE. | D14: Rien n'est filtré ; un Type de travail autre que PRE est signalé (Info). | E14: L'extraction réelle sera-t-elle limitée aux OT préventifs ? Sur quel critère ? | F14: À confirmer
A15: 8 | B15: Année planifiée | C15: L'année vient de « Date début planifiée » ; « Créé le » et « Date modif. fiche ordre » existent aussi. | D15: Année planifiée = année de la Date début planifiée. | E15: Est-ce la bonne date de référence pour rattacher un OT à une année du programme ? | F15: À confirmer
A16: 9 | B16: Statuts OT | C16: Statut utilisateur ACTI / TERM et Statut système présents dans l'extraction. | D16: Conservés dans 04 mais volontairement non exploités (hors périmètre du produit). | E16: Faut-il exclure certains statuts (ex. OT annulés) du comptage de couverture ? | F16: À confirmer
A17: 10 | B17: Référentiel programme | C17: TYPE_E « Opération spécifique » : référence technique et statut « À confirmer ». | D17: Libellé affiché tel quel, statut « À confirmer » en jaune. | E17: Quel libellé, quelle référence technique pour ce type ? | F17: À confirmer
A18: 11 | B18: Doublons programme | C18: Lignes strictement identiques dans le programme : INST-006 / TYPE_A / 2027 ; INST-010 / TYPE_A / 2027 ; INST-021 / TYPE_A / 2027 ; INST-040 / TYPE_A / 2028 ; INST-020 / TYPE_E / 2029. | D18: Conservées et signalées (●×2 dans le plan, « Doublon potentiel »). | E18: Deux interventions distinctes ou doublon d'extraction ? | F18: À confirmer
A19: 12 | B19: Périodicité | C19: Dans le programme, l'intervalle entre deux occurrences ne correspond pas toujours à la périodicité indiquée (ex. INST-017 Révision « 6 ans » en 2027 puis 2029). | D19: Aucune année n'est recalculée : seules les années de la source sont affichées. | E19: La périodicité est-elle indicative ? L'année prévue vient-elle uniquement de la GMAO ? | F19: À confirmer
A20: 13 | B20: Vue plan | C20: La vue 01 compte 104 lignes poste × opération, construites à partir du programme. | D20: Les cases se recalculent ; une nouvelle combinaison poste / opération demande de régénérer la vue. | E20: Faut-il passer le programme en Power Query, comme les OT, une fois sa source réelle connue ? | F20: À confirmer

Sheet 08_PARAMETRES
A1: Paramètres et contrôles de l'import | G1: PROTOTYPE V0.3
A2: Seules les cellules blanches encadrées se modifient. Power Query lit ces valeurs à chaque actualisation.
B5: Paramètres
B6: Année d'analyse | C6: 2027 | F6: Année mise en avant dans 01 (colonne jaune) et 02 (indicateurs, lignes grisées).
B7: Dossier de ce classeur (automatique) | C7: =IFERROR(LEFT(CELL("filename",$A$1),FIND("[",CELL("filename",$A$1))-1),"") | F7: Calculé par Excel quand le classeur est enregistré sur le poste (vide sinon).
B8: Nom du fichier d'extraction GMAO | C8: MODELE_GMAO_PREV_ANONYMISE.csv | F8: Fichier .xlsx ou .csv (séparateur ;) placé dans le même dossier que ce classeur.
B9: Chemin complet de l'extraction (facultatif) | F9: Prioritaire s'il est rempli, ex. C:\Maintenance\Extraction_GMAO.xlsx. Pas d'adresse https.
B10: Chemin utilisé par Power Query | C10: =IF(LEN(TRIM(P_CheminComplet))>0,TRIM(P_CheminComplet),P_DossierClasseur&P_NomFichierSource) -> MODELE_GMAO_PREV_ANONYMISE.csv | F10: Calculé : ne pas modifier.
B11: Feuille de l'extraction (si fichier Excel) | F11: Vide = première feuille du fichier.
B12: Longueur du code poste | C12: 9 | F12: Code poste = N premiers caractères du Poste technique (règle du test manuel : 9).
B13: Caractère attendu après le code poste | C13: - | F13: Sert au contrôle de format (« - » observé dans l'export modèle). Vide = pas de contrôle.
B14: Dernière actualisation des OT (automatique) | C14: =IFERROR(INDEX('04_DETAIL_OT'!$A$2:$AZ$2,MATCH("Importé le",'04_DETAIL_OT'!$A$1:$AZ$1,0)),"") -> 46309.508 | F14: Écrite par la requête OT_Detail à chaque « Actualiser tout ».
B15: Source des OT actuellement chargée | C15: =IFERROR(INDEX('04_DETAIL_OT'!$A$2:$AZ$2,MATCH("Fichier source",'04_DETAIL_OT'!$A$1:$AZ$1,0)),"") -> Instantané de démonstration – MODELE_GMAO_PREV_ANONYMISE.csv | F15: « Instantané de démonstration » tant que les requêtes ne sont pas installées (09_NOTICE).
B16: Date d'import du programme préventif | C16: 46308 | F16: Programme (03_DETAIL_PROGRAMME) : à mettre à jour à chaque nouvel import.
B18: Contrôles de l'import GMAO
B19: Une ligne par contrôle, recalculée à chaque actualisation. Les lignes concernées se filtrent dans 04_DETAIL_OT, colonne « Contrôle qualité ».
A20: N° | B20: Contrôle | C20: Niveau | D20: Lignes de l'export | E20: OT distincts | F20: Exemples (Ordre ou ligne) | G20: Statut
A21: 0 | B21: Lignes lues dans l'export | C21: Info | D21: 90 | E21: 90 | G21: INFO
A22: 1 | B22: Écart de structure de l'export | C22: À vérifier | D22: 0 | E22: 0 | G22: OK
A23: 2 | B23: Ordre vide | C23: À vérifier | D23: 0 | E23: 0 | G23: OK
A24: 3 | B24: OT présent sur plusieurs lignes de l'export | C24: À vérifier | D24: 0 | E24: 0 | G24: OK
A25: 4 | B25: Poste technique vide | C25: À vérifier | D25: 0 | E25: 0 | G25: OK
A26: 5 | B26: Poste technique trop court | C26: À vérifier | D26: 0 | E26: 0 | G26: OK
A27: 6 | B27: Format du Poste technique inattendu | C27: À vérifier | D27: 0 | E27: 0 | G27: OK
A28: 7 | B28: Date début planifiée vide | C28: À vérifier | D28: 0 | E28: 0 | G28: OK
A29: 8 | B29: Date début planifiée illisible | C29: À vérifier | D29: 0 | E29: 0 | G29: OK
A30: 9 | B30: Activité vide | C30: À vérifier | D30: 0 | E30: 0 | G30: OK
A31: 10 | B31: Activité mal formée | C31: À vérifier | D31: 0 | E31: 0 | G31: OK
A32: 11 | B32: Activité inconnue du référentiel | C32: À vérifier | D32: 0 | E32: 0 | G32: OK
... A37: 16 | B37: Type de travail autre que PRE | C37: Info | D37: 0 | E37: 0 | G37: OK

Sheet 09_NOTICE
A1: Notice | C1: PROTOTYPE V0.3
A2: Prototype V0.3 de programmation préventive et de couverture OT.
A5: En bref
A6: Le produit est d'abord un outil de programmation et de suivi de la maintenance préventive par poste : Site → Équipe → Poste → Année → opérations prévues (01_PLAN_PREVENTIF).
A7: La couche OT GMAO (02_COUVERTURE_OT) répond en complément à : « les OT préventifs correspondant à ce que je dois faire sont-ils bien présents dans la GMAO ? ». Ce n'est pas un suivi de tous les OT : ni statuts, ni retards, ni clôtures.
A8: Données 100 % fictives. La GMAO reste la source officielle : ne jamais corriger les données dans ce fichier.
A10: Onglets
A11: Onglet | B11: Contenu | C11: Mise à jour
A12: 01_PLAN_PREVENTIF | B12: Plan pluriannuel : une ligne par poste et opération, une colonne par année. | C12: Consultation.
A13: 02_COUVERTURE_OT | B13: Nombre d'OT distincts par année, site, équipe, poste et activité. | C13: Power Query (OT_Couverture).
A14: 03_DETAIL_PROGRAMME | B14: Programme préventif normalisé (T_Programme), une ligne par opération et par année. | C14: Remplacé à chaque import du programme.
A15: 04_DETAIL_OT | B15: OT GMAO normalisés : une ligne par couple Ordre × Activité atomique. | C15: Power Query (OT_Detail).
A16: 05_REFERENTIEL | B16: Types du programme, activités GMAO, sites et équipes connus, correspondance des postes. | C16: Référent données.
A17: 06_AVIS_UTILISATEURS | B17: Recueil des retours, une ligne par remarque. | C17: Tous les testeurs.
A18: 07_POINTS_A_VALIDER | B18: Questions métier à trancher. | C18: Équipe projet.
A19: 08_PARAMETRES | B19: Année, emplacement de l'extraction, règle du code poste, contrôles de l'import. | C19: Cellules blanches seulement.
A20: 09_NOTICE | B20: Ce mode d'emploi.
A21: 10_CODE_M | B21: Code M des trois requêtes, à coller une seule fois (voir « Installer Power Query »).
A23: Règles de l'import GMAO
A24: Règle | B24: Ce que fait l'import | C24: Cas particuliers
A25: Site / Équipe | B25: Site = « Groupe gestionnaires » ; Équipe = « Poste travail princ. ». | C25: Correspondances observées lors du test manuel.
A26: Code poste | B26: 9 premiers caractères du « Poste technique » (Excel : =GAUCHE(Poste technique;9) ; Power Query : Text.Start([Poste technique], 9)). Longueur réglable dans 08. | C26: Poste vide, trop court ou de format inattendu : ligne gardée et signalée.
A27: Année planifiée | B27: Année de la « Date début planifiée ». | C27: Date vide ou illisible : ligne gardée et signalée.
A28: Activité | B28: Découpée sur « + », espaces retirés, en majuscules : « EC+PIS+FILTRE » donne 3 lignes (EC, PIS, FILTRE). | C28: Activité vide, mal formée ou inconnue du référentiel : signalée.
A29: Doublons | B29: Un même couple Ordre + Activité n'est gardé qu'une fois ; la ligne gardée indique les lignes de l'export regroupées. | C29: Signalé : « Couple Ordre + Activité en double ».
A30: Comptage | B30: Couverture = nombre d'OT DISTINCTS (numéro d'Ordre) par année, site, équipe, poste et activité. | C30: Un tableau croisé sur 04_DETAIL_OT peut utiliser « Nombre » : chaque couple n'y figure qu'une fois.
A31: Colonnes | B31: Les 24 en-têtes de l'extraction sont repris tels quels (espaces de fin retirés, ex. « Typologie »). | C31: 6 obligatoires : si l'une manque, l'actualisation s'arrête avec un message qui la nomme.
A33: Installer Power Query (une seule fois, Excel Desktop sous Windows)
A34: 1. Enregistrer ce classeur sur le poste, dans le dossier de l'extraction GMAO. Dans 08_PARAMETRES, vérifier le nom du fichier (ou saisir son chemin complet).
A35: 2. Données › Obtenir des données › À partir d'autres sources › Requête vide. Accueil › Éditeur avancé : coller le code de OT_Detail (fichier OT_Detail.pq ou onglet 10_CODE_M), OK. Renommer la requête « OT_Detail » (volet Paramètres d'une requête › Nom).
A36: 3. Recommencer avec OT_Couverture, puis OT_Controles (noms exacts : les requêtes s'appellent entre elles). Puis Accueil › Fermer et charger dans… › Créer uniquement la connexion.
A37: 4. Effacer les instantanés de démonstration : 04_DETAIL_OT, 02_COUVERTURE_OT à partir de A8 et 08_PARAMETRES à partir de A20 (Données › Filtrer pour retirer les flèches, puis sélection et Suppr).
A38: 5. Volet Requêtes et connexions : clic droit › Charger dans… › Tableau › Feuille de calcul existante : OT_Detail en ='04_DETAIL_OT'!$A$1, OT_Couverture en ='02_COUVERTURE_OT'!$A$8, OT_Controles en ='08_PARAMETRES'!$A$20.
A39: Si Excel demande les niveaux de confidentialité, choisir « Organisationnel » pour le classeur et pour le fichier. Message « Formula.Firewall » : Données › Obtenir des données › Options de requête › Classeur actif › Confidentialité › Ignorer les niveaux de confidentialité (si la politique interne l'autorise).
A41: Actualiser (à chaque nouvelle extraction)
A42: Remplacer le fichier d'extraction (même nom, ou nouveau nom dans 08_PARAMETRES), puis Données › Actualiser tout. Détail, couverture, contrôles et indicateurs se mettent à jour, y compris pour un nouvel OT, une nouvelle année, activité, site ou équipe.
A43: Lire ensuite les contrôles (08_PARAMETRES) : tout statut « À VÉRIFIER » se filtre dans 04_DETAIL_OT, colonne « Contrôle qualité ». Ajouter au référentiel (05) un site, une équipe ou une activité validés.
A44: Programme préventif : remplacer les lignes de 03_DETAIL_PROGRAMME, puis lire le contrôle de la ligne 6 de 01_PLAN_PREVENTIF. En V0.3, une nouvelle combinaison poste / opération demande de régénérer la vue (outils/construire_prototype_v03.py).
A46: Power BI et comparaison future
... A48: Comparaison prévu / OT (prévu + OT présent, prévu sans OT, OT hors programme) : préparée mais pas activée. Il faut d'abord valider la clé de rapprochement (T_Correspondance_Postes et correspondance des activités, onglet 05).

Sheet 10_CODE_M
A1: Code M des requêtes Power Query
A2: Copier un bloc (cellules de la colonne A, de « let » à la dernière ligne) dans l'Éditeur avancé.
A5: Requête « OT_Detail » – fichier OT_Detail.pq – chargement : 04_DETAIL_OT!A1
A6: // =====================================================================
A7: // OT_Detail - import et normalisation de l'extraction GMAO (OT préventifs)
A8: // Résultat : une ligne par couple Ordre x Activité atomique, sans doublon.
A9: // Chargement : tableau dans l'onglet 04_DETAIL_OT, cellule A1.
A10: // Paramètres (08_PARAMETRES) : P_CheminSource, P_FeuilleSource,
A11: // P_LongueurCodePoste, P_SeparateurCodePoste.
A12: // Référentiels (05_REFERENTIEL) : T_Ref_Activites, T_Ref_Sites.
A13: // =====================================================================
A14: let
... A385: Resultat
